plain_flags_sdk-1.0.3.dist-info/licenses/LICENSE.txt
plainflags/__init__.py
plainflags/constrainer.py
plainflags/constraint.py
plainflags/flagstate.py
plainflags/plainflags.py
plain_flags_sdk-1.0.3.dist-info/METADATA
plain_flags_sdk-1.0.3.dist-info/WHEEL
plain_flags_sdk-1.0.3.dist-info/top_level.txt
plain_flags_sdk-1.0.3.dist-info/RECORD
