Metadata-Version: 2.4
Name: plain-flags-sdk
Version: 1.0.3
Summary: Python SDK for the Plain Flags free feature flag system
Home-page: https://plainflags.dev
Author: Andrei Leonte
Author-email: Andrei Leonte <andrei.leonte.dev@gmail.com>
Project-URL: Homepage, https://plainflags.dev
Classifier: Programming Language :: Python :: 3
Classifier: Operating System :: OS Independent
Classifier: Intended Audience :: Developers
Classifier: Topic :: Software Development :: Libraries :: Python Modules
Requires-Python: >=3.6
License-File: LICENSE.txt
Requires-Dist: aiohttp
Dynamic: author
Dynamic: home-page
Dynamic: license-file
Dynamic: requires-python
